{
  "id": "TRC-002",
  "name": "Mintable",
  "description": "Mintable indicates that the token allows for potential malicious minting. The deployer can continuously mint new tokens, draining the liquidity pool for profit. This can trigger a massive sell-off, causing the coin price to plummet and leading to significant losses for other token holders.",
  "samples": [
    {
      "name": "01.sol"
    },
    {
      "name": "02.sol"
    },
    {
      "name": "03.sol"
    },
    {
      "name": "04.sol"
    }
  ]
}